i18nconverter/__init__.py
i18nconverter/main.py
i18nconverter/utils/__init__.py
i18nconverter/utils/gspreadsheet_to_json.py
i18nconverter/utils/json_to_kv.py
i18nconverter/utils/kv_to_gspreadsheet.py
i18nconverter/utils/utils_google.py
i18nconverter-0.0.4.dist-info/LICENSE
i18nconverter-0.0.4.dist-info/METADATA
i18nconverter-0.0.4.dist-info/WHEEL
i18nconverter-0.0.4.dist-info/entry_points.txt
i18nconverter-0.0.4.dist-info/top_level.txt
i18nconverter-0.0.4.dist-info/RECORD
