Metadata-Version: 2.1
Name: i18nconverter
Version: 0.0.4
Summary: A CLI application for managing i18n Json files.
Author-email: Andrea Carmisciano <andrea.carmisciano@gmail.com>
Project-URL: Homepage, https://github.com/acarmisc/i18n-json-spreadsheet
Project-URL: Source, https://github.com/acarmisc/i18n-json-spreadsheet
License-File: LICENSE
Requires-Dist: cachetools ==5.3.2
Requires-Dist: certifi ==2023.7.22
Requires-Dist: charset-normalizer ==3.3.2
Requires-Dist: click ==8.1.7
Requires-Dist: google-auth ==2.23.4
Requires-Dist: google-auth-oauthlib ==1.1.0
Requires-Dist: gspread ==5.12.0
Requires-Dist: idna ==3.4
Requires-Dist: oauthlib ==3.2.2
Requires-Dist: pyasn1 ==0.5.0
Requires-Dist: pyasn1-modules ==0.3.0
Requires-Dist: requests ==2.31.0
Requires-Dist: requests-oauthlib ==1.3.1
Requires-Dist: rsa ==4.9
Requires-Dist: urllib3 ==1.26.15
